qwilfish/__init__.py
qwilfish/__main__.py
qwilfish/_version.py
qwilfish/constants.py
qwilfish/derivation_tree.py
qwilfish/grammar.py
qwilfish/grammar_utils.py
qwilfish/main.py
qwilfish/parser.py
qwilfish/plugin_loader.py
qwilfish/qwilfuzzer.py
qwilfish/session.py
qwilfish/session_builder.py
qwilfish/configuration/README.md
qwilfish/configuration/__init__.py
qwilfish/configuration/default.yaml
qwilfish/plugins/README.md
qwilfish/plugins/__init__.py
qwilfish/plugins/arbiter/__init__.py
qwilfish/plugins/arbiter/basic_arbiter.py
qwilfish/plugins/arbiter/wordle_arbiter.py
qwilfish/plugins/courier/__init__.py
qwilfish/plugins/courier/raw_socket_courier.py
qwilfish/plugins/courier/udp_socket_courier.py
qwilfish/plugins/grammar/__init__.py
qwilfish/plugins/grammar/coap_grammar.py
qwilfish/plugins/grammar/lldp_grammar.py
qwilfish/plugins/grammar/simplified_lldp_grammar.py
qwilfish/plugins/grammar/wordle_grammar.py
qwilfish/plugins/reward_function/__init__.py
qwilfish/plugins/reward_function/memory_chasing_fitness_function.py
qwilfish/plugins/reward_function/wordle_reward_function.py
qwilfish/results_db/__init__.py
qwilfish/results_db/database.py
qwilfish/results_db/dataclasses.py
qwilfish-0.4.1.dist-info/LICENSE
qwilfish-0.4.1.dist-info/METADATA
qwilfish-0.4.1.dist-info/WHEEL
qwilfish-0.4.1.dist-info/entry_points.txt
qwilfish-0.4.1.dist-info/top_level.txt
qwilfish-0.4.1.dist-info/RECORD
