Metadata-Version: 2.1
Name: qwilfish
Version: 0.4.1
Summary: Python package for grammar-based Layer 2 fuzzing
Home-page: https://gitlab.com/zluudg/qwilfish
Author: Leon Fernandez
Author-email: leonfe@kth.se
Keywords: ethernet fuzzing
Classifier: Programming Language :: Python :: 3
Classifier: Development Status :: 2 - Pre-Alpha
Classifier: License :: OSI Approved :: MIT License
Requires-Python: >=3.10
License-File: LICENSE
Requires-Dist: pyyaml (>=6.0)
Requires-Dist: qwilprobe (>=0.2)
